[
  {
    "ilan_turu": "Kayıp",
    "baslik": "ACİL KAYIP KEDİ",
    "aciklama": "Kartal-Çavuşoğlu Muhtarligi bölgesinden kayboldu. Dişi kisir degil 8 aylik. Yaklasik 1 aydan beri kayip. o bolgede aramadigimiz yer kalmadi, araba motoru weya kamyon arkasinda yer degisikligi olmuş olabilir.",
    "konum": "İstanbul / Kartal",
    "tarih1": "13 Saat Önce",
    "tarih2": "2026-03-18T20:34:44Z",
    "kategori": "Kedi",
    "gorsel": "https://www.gorenduyan.com/images/ad/2026/03/18/202603182339-23857-65981.jpg",
    "link": "https://www.gorenduyan.com/acil-kayip-kedi-21488"
  },
  {
    "ilan_turu": "Kayıp",
    "baslik": "KAYIP KEDİ BOSTANCIK CADDESİ",
    "aciklama": "Altındağ bostancık caddesi bostancık sürücü kursu önünde bulduk erkek veterinere götürdük çipi yok tasması var ev kedisi",
    "konum": "Ankara - Bostancık",
    "tarih1": "14 Saat Önce",
    "tarih2": "2026-03-18T19:34:46Z",
    "kategori": "Kedi",
    "gorsel": "https://www.gorenduyan.com/images/ad/2026/03/18/202603182250-23856-88294.jpg",
    "link": "https://www.gorenduyan.com/kayip-kedi-bostancik-caddesi-21487"
  },
  {
    "ilan_turu": "Kayıp",
    "baslik": "fethi ahmet cami orada kaybolmuştur",
    "aciklama": "fethi ahmet cami orada kaybolmuştur siyah tüylü bir kedi boynunda tasması var sarı gözlü lütfen yardımcı olalım ev kedisidir dışarda yaşaması mümkün değil Allah rızası için",
    "konum": "Elazığ / Merkez",
    "tarih1": "21 Saat Önce",
    "tarih2": "2026-03-18T12:34:47Z",
    "kategori": "Kedi",
    "gorsel": "https://www.gorenduyan.com/images/ad/2026/03/18/202603181553-23853-63719.jpg",
    "link": "https://www.gorenduyan.com/fethi-ahmet-cami-orada-kaybolmustur-21485"
  },
  {
    "ilan_turu": "Kayıp",
    "baslik": "Kayıp Kedi- Tarsus Kırklarsırtı",
    "aciklama": "Kedimiz 18 Mart sabah saatlerinde kırklarsırtı muhtarlığı civarında kaybolmuştur. Kesik kulak scottishtir. Adı lumi.",
    "konum": "Mersin - Tarsus",
    "tarih1": "21 Saat Önce",
    "tarih2": "2026-03-18T12:34:48Z",
    "kategori": "Kedi",
    "gorsel": "https://www.gorenduyan.com/images/ad/2026/03/18/202603181536-23852-71270.jpg",
    "link": "https://www.gorenduyan.com/kayip-kedi-tarsus-kirklarsirti-21484"
  },
  {
    "ilan_turu": "Kayıp",
    "baslik": "KAYIP KEDI MIYA ARANIYORR",
    "aciklama": "Kedim miya şemsitebrizi mahallesi civarında kayboldu gören duyan olursa lütfen lütfenbana ulaşabilirmi tel:05061758311",
    "konum": "Konya Karatay, Mevlana,",
    "tarih1": "22 Saat Önce",
    "tarih2": "2026-03-18T11:34:50Z",
    "kategori": "Kedi",
    "gorsel": "https://www.gorenduyan.com/images/ad/2026/03/18/202603181442-23851-48147.jpg",
    "link": "https://www.gorenduyan.com/kayip-kedi-miya-araniyorr-21483"
  },
  {
    "ilan_turu": "Kayıp",
    "baslik": "Kayıp köpek- Silivri",
    "aciklama": "Silivri Gümüşyaka kayıp köpek ilanı\r\n\r\nCanımız Luna Silivri Gümüşyaka'da 2 gün önce kaybolmuştur.\r\n\r\nDişidir 3 yaşında \r\n\r\nBULANA 50 BİN TL ÖDÜR VARDIR",
    "konum": "İstanbul - Gümüşyaka",
    "tarih1": "17 Saat Önce",
    "tarih2": "2026-03-18T16:34:53Z",
    "kategori": "Köpek",
    "gorsel": "https://www.gorenduyan.com/images/ad/2026/03/18/202603181914-23855-56496.jpg",
    "link": "https://www.gorenduyan.com/kayip-kopek-silivri-21486"
  },
  {
    "ilan_turu": "Sahiplendirme",
    "baslik": "Scottish Kedisi",
    "aciklama": "Uysal bir kedi tuvalet sorunu yokalan kişinin kısırlastırmasını istiyorum.",
    "konum": "Ankara / Mamak",
    "tarih1": "18.03.2026",
    "tarih2": "2026-03-18T00:00:00Z",
    "kategori": "Kedi",
    "gorsel": "https://www.petcim.com/pictures_ilan/mini_2784a8b6e3fdc6cb6bca3ff9301f4b2e.jpeg",
    "link": "https://www.petcim.com/kedi-scottish-kedisi-ilandetay-1348581"
  },
  {
    "ilan_turu": "Sahiplendirme",
    "baslik": "Scottish fold kedisi",
    "aciklama": "Detaylı bilgi için whatsapp tan mesaj atabilirsinizSamsun ilkadimSadece whatsapp",
    "konum": "Samsun / İlkadım",
    "tarih1": "18.03.2026",
    "tarih2": "2026-03-18T00:00:00Z",
    "kategori": "Kedi",
    "gorsel": "https://www.petcim.com/pictures_ilan/mini_87a7fed8d8e4fe581915c6f5590b38ed.jpg",
    "link": "https://www.petcim.com/kedi-scottish-fold-kedisi-ilandetay-1348564"
  },
  {
    "ilan_turu": "Sahiplendirme",
    "baslik": "BİRİTİSH SHORTHAİR YAVRULARİMİZ",
    "aciklama": "YAVRULARIMIZ GAYET SAĞLIKLI KONTROLLERİ YAPILDIKURU MAMA VE WC EGİTİMİNİ ALDİLAREVİNİZİN YENİ NEŞE KAYNAKLARI YENİ BİR EVLATDİĞER BİLGİLERİ İÇİN WP DEN ULASABİLİRSİNİZ",
    "konum": "Samsun / İlkadım",
    "tarih1": "18.03.2026",
    "tarih2": "2026-03-18T00:00:00Z",
    "kategori": "Kedi",
    "gorsel": "https://www.petcim.com/pictures_ilan/mini_fa5bf67c98fb7c749a4c062890788424.jpg",
    "link": "https://www.petcim.com/kedi-biritish-shorthair-yavrularimiz-ilandetay-1348559"
  },
  {
    "ilan_turu": "Sahiplendirme",
    "baslik": "BİRİTİSH SHORTHAİR YAVRULARIMIZ",
    "aciklama": "WC EĞİTİMİNİ TAMAMLADILAR KURU MAMAYA BAŞLADILAR.SAĞLIK KONTROLLERİ YAPILDIGAYET SAGLİKLİLAREVİNİZİN NEŞESİ OLACAK YENİ BİR EVLAT.DİĞER BİLGİLERİ İÇİN WP DEN ULASABİLİRSİNİZ.",
    "konum": "Samsun / İlkadım",
    "tarih1": "18.03.2026",
    "tarih2": "2026-03-18T00:00:00Z",
    "kategori": "Kedi",
    "gorsel": "https://www.petcim.com/pictures_ilan/mini_bb0bf5f8fe899b45a81b700bf83e3712.jpg",
    "link": "https://www.petcim.com/kedi-biritish-shorthair-yavrularimiz-ilandetay-1348557"
  },
  {
    "ilan_turu": "Sahiplendirme",
    "baslik": "British longhair yavru kedimiz",
    "aciklama": "1:30 aylık yavru kedi Bir erkek bir kız sahiplendirilecektir detaylı bilgi için WhatsApp'tan yazabilirsiniz",
    "konum": "Antalya / Kepez",
    "tarih1": "18.03.2026",
    "tarih2": "2026-03-18T00:00:00Z",
    "kategori": "Kedi",
    "gorsel": "https://www.petcim.com/pictures_ilan/mini_b7af0ba524138492a358ba8c01785066.jpeg",
    "link": "https://www.petcim.com/kedi-british-longhair-yavru-kedimiz-ilandetay-1348550"
  },
  {
    "ilan_turu": "Sahiplendirme",
    "baslik": "A kalite Golden NY 12 dişi yavru british",
    "aciklama": "43 günlük A kalite GoldennNY 12 dişi yavru. Mama ve tuvalet eğitimi tamdır. Anne ve Baba yurt dışı orijinal yavru",
    "konum": "İstanbul / Maltepe",
    "tarih1": "18.03.2026",
    "tarih2": "2026-03-18T00:00:00Z",
    "kategori": "Kedi",
    "gorsel": "https://www.petcim.com/pictures_ilan/mini_eb22aa5ee53aa09f7ae2ff4daffffb68.jpeg",
    "link": "https://www.petcim.com/kedi-a-kalite-golden-ny-12-disi-yavru-british-ilandetay-1348546"
  },
  {
    "ilan_turu": "Sahiplendirme",
    "baslik": "British shorthair kediler",
    "aciklama": "British shorthair Silver ns11 (1.5 yaş dişi)British shorthair silver ns1133 (2 yaş dişi)",
    "konum": "Ankara / Etimesgut",
    "tarih1": "18.03.2026",
    "tarih2": "2026-03-18T00:00:00Z",
    "kategori": "Kedi",
    "gorsel": "https://www.petcim.com/pictures_ilan/mini_8f639c10a7d5f6db65e4f4715bd7b9f8.jpg",
    "link": "https://www.petcim.com/kedi-british-shorthair-kediler-ilandetay-1348545"
  },
  {
    "ilan_turu": "Sahiplendirme",
    "baslik": "IRK GARANTİLİ YAVRULARIMIZ",
    "aciklama": "SAFKAN VE IRK GARANTİLİ YAVRULARIMIZKURU MAMA YAS MAMA YİYORGUNU GELEN ASILARI OLMUSTURVETERİNER KONTROLU ALTINDA TESLİM EDİYORUZ",
    "konum": "Ankara / Keçiören",
    "tarih1": "19.03.2026",
    "tarih2": "2026-03-19T00:00:00Z",
    "kategori": "Köpek",
    "gorsel": "https://www.petcim.com/pictures_ilan/mini_f98572b4c3c62d3dad16ac10a26405a1.jpg",
    "link": "https://www.petcim.com/kopek-irk-garantili-yavrularimiz-ilandetay-1349085"
  },
  {
    "ilan_turu": "Sahiplendirme",
    "baslik": "ORJİNAL TOY POODLE YAVRULARIMIZ",
    "aciklama": "SAFKAN VE IRK GARANTİLİ YAVRULARIMIZKURU MAMA YAS MAMA YİYOR GUNU GELEN ASILARI OLMUSTUR81 İLE GONDERİMİZ MEVCUTTUR",
    "konum": "Ankara / Keçiören",
    "tarih1": "19.03.2026",
    "tarih2": "2026-03-19T00:00:00Z",
    "kategori": "Köpek",
    "gorsel": "https://www.petcim.com/pictures_ilan/mini_ebcc922c168ab252955ce59b6a97909b.jpg",
    "link": "https://www.petcim.com/kopek-orjinal-toy-poodle-yavrularimiz-ilandetay-1349084"
  },
  {
    "ilan_turu": "Sahiplendirme",
    "baslik": "SAFKAN VE IRK GARANTİLİ YAVRULARIMIZ",
    "aciklama": "SAFKAN VE IRK GARANTİLİ YAVRULARIMIZGUNU GELEN ASILARI OLMUSTURVETERİNER KONTROLU ALTINDA TESLİM EDİYORUZ",
    "konum": "Ankara / Keçiören",
    "tarih1": "19.03.2026",
    "tarih2": "2026-03-19T00:00:00Z",
    "kategori": "Köpek",
    "gorsel": "https://www.petcim.com/pictures_ilan/mini_f7a2e61896b6bbe64fbc2038ada64a2a.jpg",
    "link": "https://www.petcim.com/kopek-safkan-ve-irk-garantili-yavrularimiz-ilandetay-1349083"
  },
  {
    "ilan_turu": "Sahiplendirme",
    "baslik": "Dişi 3 yaşında Pomerian kızımız",
    "aciklama": "3 yaşında dişidirDenizlideyizsaltak caddesindeyiz Petshopuz2 sefer anne olduyer sorunundan dolayı sahiplendirme yapacağızdaha fazla bilgi için ulaşabilirsiniz",
    "konum": "Denizli / Merkezefendi",
    "tarih1": "19.03.2026",
    "tarih2": "2026-03-19T00:00:00Z",
    "kategori": "Köpek",
    "gorsel": "https://www.petcim.com/pictures_ilan/mini_788f86cbaa3e20ee580997a24f8b4407.jpeg",
    "link": "https://www.petcim.com/kopek-disi-3-yasinda-pomerian-kizimiz-ilandetay-1349033"
  },
  {
    "ilan_turu": "Sahiplendirme",
    "baslik": "Sevimli Elsa  çok oyuncu, çok meraklı ama bi o kadar tatlıdır",
    "aciklama": "Merhaba ismi Elsa 10 aylıktır, kısırlaştırılmıştır, cinsi Ankara kedisidir, aynı zamanda çipi mevcuttur, kedimiz duymuyor kendisi fakat tam bir oyun kedisidir sahiplendirirken mevcut bütün eşyaları ile sahiplendirilecektir.",
    "konum": "Isparta",
    "tarih1": "19.03.2026",
    "tarih2": "2026-03-19T00:00:00Z",
    "kategori": "Kedi",
    "gorsel": "https://images.petlebi.com/v7/_ptlb/up/adopt/sm_1135926_1773911373_1056.jpg",
    "link": "https://sosyal.petlebi.com/kedi-sahiplenme/1135926-sevimli-elsa-cok-oyuncu-cok-merakli-ama-bi-o-kadar-tatlidir"
  },
  {
    "ilan_turu": "Sahiplendirme",
    "baslik": "Erzincan kedisi",
    "aciklama": "Merhaba zeytin erzincan kemaliye de ben burada öğrenciyim zeytine bakıyorum ama mezun olacağım benden sonra zeytine kimse bakmaz alacak kişi için erzincan da hayvanın çipini taktırabilirim ve samsuna otobüs ile yollayabilirim dişi kedi kendisi kısır değil çip şartı ile sahiplendiriyorum",
    "konum": "Elazığ",
    "tarih1": "19.03.2026",
    "tarih2": "2026-03-19T00:00:00Z",
    "kategori": "Kedi",
    "gorsel": "https://images.petlebi.com/v7/_ptlb/up/adopt/sm_1135927_1773911821_7417.jpg",
    "link": "https://sosyal.petlebi.com/kedi-sahiplenme/1135927-erzincan-kedisi"
  },
  {
    "ilan_turu": "Sahiplendirme",
    "baslik": "Hamile kedimize gecici yuva ariyorum",
    "aciklama": "Hamile kedimize 3 ay gibi bir surelik gecici yuva ariyorum",
    "konum": "Gaziantep",
    "tarih1": "19.03.2026",
    "tarih2": "2026-03-19T00:00:00Z",
    "kategori": "Kedi",
    "gorsel": "https://images.petlebi.com/v7/_ptlb/up/adopt/sm_1135917_1773904796_2479.jpg",
    "link": "https://sosyal.petlebi.com/kedi-sahiplenme/1135917-hamile-kedimize-gecici-yuva-ariyorum"
  },
  {
    "ilan_turu": "Sahiplendirme",
    "baslik": "Sütlü kadayıf denemek ister misiniz",
    "aciklama": "Çipli erkek çok mu çok yemek isteyeceğiniz bir exotix longhair",
    "konum": "Antalya",
    "tarih1": "19.03.2026",
    "tarih2": "2026-03-19T00:00:00Z",
    "kategori": "Kedi",
    "gorsel": "https://images.petlebi.com/v7/_ptlb/up/adopt/sm_1135913_1773897542_5481.jpg",
    "link": "https://sosyal.petlebi.com/kedi-sahiplenme/1135913-sutlu-kadayif-denemek-ister-misiniz"
  },
  {
    "ilan_turu": "Sahiplendirme",
    "baslik": "Sevgi Dolu Yuva Arayan Uysal Dost 🐱",
    "aciklama": "Bu tatlı dostumuz şu an Samsun Atakum'da yaşamaktadır. Orta boy olup oldukça uysal ve insanlarla iyi anlaşmakta. Dişi kedi olup kısırlaştırılmadı. Hiç sokak görmedi, evde doğdu büyüdü. İnsanlara ve misafire alışık, yabancilasmiyor. Ev ortamına uyumlu, sevgiye çok açık ve oyuncu bir karaktere sahiptir. Tuvalet eğitimi var.",
    "konum": "Samsun",
    "tarih1": "19.03.2026",
    "tarih2": "2026-03-19T00:00:00Z",
    "kategori": "Kedi",
    "gorsel": "https://images.petlebi.com/v7/_ptlb/up/adopt/sm_1135909_1773877906_3819.jpg",
    "link": "https://sosyal.petlebi.com/kedi-sahiplenme/1135909-sevgi-dolu-yuva-arayan-uysal-dost"
  },
  {
    "ilan_turu": "Sahiplendirme",
    "baslik": "Sıcak bir yuva arıyoruz",
    "aciklama": "🐱 Sahiplendirilecek: 5 Yaşında British Shorthair Erkek Kedi\nYurt dışına taşınmam nedeniyle 5 yaşındaki British Shorthair cinsi kedim için sevgi dolu bir yuva arıyorum.\nKedi hakkında:\n∙\t🔵 Cinsi: British Shorthair\n∙\t🎂 Yaşı: 5 yaş\n∙\t💉 Aşıları tam ve güncel\n∙\t📋 Mikroçipi mevcut\n∙\t📄 Tam sahip devri yapılabilir (tüm belgeler hazır)\nKarakteri:\nİnsan canlısı, oyuncu ve son derece yumuşak huylu bir kedi. Ziyaretçilere alışkın, evde huzurlu bir ortam yaratıyor.",
    "konum": "İstanbul",
    "tarih1": "18.03.2026",
    "tarih2": "2026-03-18T00:00:00Z",
    "kategori": "Kedi",
    "gorsel": "https://images.petlebi.com/v7/_ptlb/up/adopt/sm_1135886_1773858884_8952.jpg",
    "link": "https://sosyal.petlebi.com/kedi-sahiplenme/1135886-sicak-bir-yuva-ariyoruz"
  },
  {
    "ilan_turu": "Sahiplendirme",
    "baslik": "British eğitimli kedimiz",
    "aciklama": "Aşıları yapılmış kısırlaştırılmış tuvalet eğitimi vardır",
    "konum": "Diyarbakır",
    "tarih1": "18.03.2026",
    "tarih2": "2026-03-18T00:00:00Z",
    "kategori": "Kedi",
    "gorsel": "https://images.petlebi.com/v7/_ptlb/up/adopt/sm_1135874_1773855787_7875.jpg",
    "link": "https://sosyal.petlebi.com/kedi-sahiplenme/1135874-british-egitimli-kedimiz"
  },
  {
    "ilan_turu": "Sahiplendirme",
    "baslik": "ACİL YUVA ARIYORUZ",
    "aciklama": "Ben iggyi 1.5 ay önce sokaktan buldum ve kıyamayıp aldım çipsizdi sonra kısırlaştırdım ama annem eski kedimin vefatından sonra başka bir kediden rahatsız oluyor belediyeye bırakmaya çalışıyorlar lütfen bu çocuğa yuva olabilcek birisi ulaşsın bana",
    "konum": "İstanbul",
    "tarih1": "18.03.2026",
    "tarih2": "2026-03-18T00:00:00Z",
    "kategori": "Kedi",
    "gorsel": "https://images.petlebi.com/v7/_ptlb/up/adopt/sm_1135872_1773855211_832.jpg",
    "link": "https://sosyal.petlebi.com/kedi-sahiplenme/1135872-acil-yuva-ariyoruz"
  },
  {
    "ilan_turu": "Sahiplendirme",
    "baslik": "Çok tatlı bir kedimiz dişi",
    "aciklama": "Adı maya 4 aylık dişi cana yakın",
    "konum": "Mersin",
    "tarih1": "18.03.2026",
    "tarih2": "2026-03-18T00:00:00Z",
    "kategori": "Kedi",
    "gorsel": "https://images.petlebi.com/v7/_ptlb/up/adopt/sm_1135863_1773850386_6163.jpg",
    "link": "https://sosyal.petlebi.com/kedi-sahiplenme/1135863-cok-tatli-bir-kedimiz-disi"
  },
  {
    "ilan_turu": "Sahiplendirme",
    "baslik": "Yanlızlıgın dostu",
    "aciklama": "Aşıları tam sevimli dostum hastalıktan dolayı benden ayrılıyor insancıl dostum beni hiç üzmedi şimdi ise ona sevgi dolu bir aile arıyorum",
    "konum": "Adana",
    "tarih1": "18.03.2026",
    "tarih2": "2026-03-18T00:00:00Z",
    "kategori": "Kedi",
    "gorsel": "https://images.petlebi.com/v7/_ptlb/up/adopt/sm_1135848_1773846786_3415.jpg",
    "link": "https://sosyal.petlebi.com/kedi-sahiplenme/1135848-yanlizligin-dostu"
  },
  {
    "ilan_turu": "Sahiplendirme",
    "baslik": "oğlumu yeni yuvasını verecem",
    "aciklama": "Yeni taşındığım ortam maalesef uygun olmadığı için çok sevdiğim kedim Bulut’u sahiplendirmek zorundayım.• 1,5 yaşında\n• Tüm aşıları eksiksiz yapılmıştır\n• Çipli ve üzerime kayıtlıdır\n• Sağlıklı, uysal ve insan canlısıdırOnu sahiplenecek kişinin gerçekten ilgili, sorumluluk sahibi ve güzel bir yuva sunabilecek biri olmasını önemsiyorum.Detaylı bilgi için Whatsapptan yazın\n📞 0552 735 34 36",
    "konum": "İstanbul",
    "tarih1": "18.03.2026",
    "tarih2": "2026-03-18T00:00:00Z",
    "kategori": "Kedi",
    "gorsel": "https://images.petlebi.com/v7/_ptlb/up/adopt/sm_1135830_1773843349_3052.jpg",
    "link": "https://sosyal.petlebi.com/kedi-sahiplenme/1135830-oglumu-yeni-yuvasini-verecem"
  },
  {
    "ilan_turu": "Sahiplendirme",
    "baslik": "Şiddet mağduru Duman",
    "aciklama": "Duman sokak kedisi..Kısırlaştırıldı fakat site binasına giriyor diye bi cani tarafından hem dövüldü hemde ormana bırakıldı...Yolunu uzun zaman geçsede buldu..Fakat geldiğinde bir deri bir kemik kalmış tüyleri dökülmüştü..Gecici yuvaya alındı..Neler başına geldi bilmiyorum cok agrasif ve güvensiz artık .Ani hareketlerde korkuyor sinirleniyor ani korku saldırıları olabiliyor..Korkmadan onun  bu korkusunu yenmesine yardımcı olabilecek sabırlı onu sakinleştirebilecek her koşulda yanında olabilecek sıkılmadan güven verebilecek kalbini ona açacak \"gercek hayvanseverler\" iletişime geçsin lütfen. Gecici yuvasında son 1 haftası kaldı ..ya tekrar yerine bırakılacak ya da barınaga verilecek ..Şiddet mağduru Dumanı kurtaralım lütfen..mesaj yada WhatsApp yoluyla  iletişime gecebilirsiniz..DUMAN A UMUT OLUN..",
    "konum": "Yalova",
    "tarih1": "19.03.2026",
    "tarih2": "2026-03-19T00:00:00Z",
    "kategori": "Kedi",
    "gorsel": "https://images.petlebi.com/v7/_ptlb/up/adopt/sm_1135912_1773890568_885.jpg",
    "link": "https://sosyal.petlebi.com/kedi-sahiplenme/1135912-siddet-magduru-duman"
  },
  {
    "ilan_turu": "Sahiplendirme",
    "baslik": "Pitbull melezi, 8 aylık erkek ömürlük takip sartli yuvasını ariyoruz",
    "aciklama": "Anneleri dört günlükken zehirlendi insan tarafından biberonla büyütüldüler, iyi huylu sakin mizacli insan seven bir çocuk. Sahiplendirme sözleşmesi kısırlaştırma sartlidir.",
    "konum": "İzmir",
    "tarih1": "18.03.2026",
    "tarih2": "2026-03-18T00:00:00Z",
    "kategori": "Köpek",
    "gorsel": "https://images.petlebi.com/v7/_ptlb/up/adopt/sm_1135827_1773842446_9271.jpg",
    "link": "https://sosyal.petlebi.com/kopek-sahiplenme/1135827-pitbull-melezi-8-aylik-erkek-omurluk-takip-sartli-yuvasini-ariyoruz"
  },
  {
    "ilan_turu": "Sahiplendirme",
    "baslik": "AŞILARI TAM, KISIR, TUVALET EĞİTİMLİ OĞLUŞ ÖMÜRLÜK YUVASINI ARIYOR BALÇOVA",
    "aciklama": "6 YAŞINDA AŞILARI TAM EĞİTİMLİ SAĞLIK SORUNU OLMAYAN COCKER OĞLUŞ JOKER ÖMÜRLÜK YUVASINI ARIYOR İZMİR\n05384433993 Balçova\nEşyalara zarar verme huyu yok çok uslu. Daha önce başka kedi veya köpekle yaşamadığı için onlarla uyumu nasıl olur bilinmiyor. Detaylı bilgi ve sahiplenmek için ilandaki telefon numarasını arayınız.",
    "konum": "İzmir",
    "tarih1": "18.03.2026",
    "tarih2": "2026-03-18T00:00:00Z",
    "kategori": "Köpek",
    "gorsel": "https://images.petlebi.com/v7/_ptlb/up/adopt/sm_1135899_1773865029_4456.jpg",
    "link": "https://sosyal.petlebi.com/kopek-sahiplenme/1135899-asilari-tam-kisir-tuvalet-egitimli-oglus-omurluk-yuvasini-ariyor-balcova"
  },
  {
    "ilan_turu": "Sahiplendirme",
    "baslik": "Sokağa Terketilmiş Kırma Yavru",
    "aciklama": "Kapıya terkedilmiş yavru kırma köpek. Cinsiyetinden emin değiliz fakat golden kırma olduğunu düşünüyoruz. Kocaeli - başiskeledeyiz. Bu yavruya kalıcı yuvasını arıyoruz.Buraya atılan mesajları göremeyebiliriz bu sebeple telefonla iletişim kutmanızı rica ediyoruz.",
    "konum": "Kocaeli",
    "tarih1": "18.03.2026",
    "tarih2": "2026-03-18T00:00:00Z",
    "kategori": "Köpek",
    "gorsel": "https://images.petlebi.com/v7/_ptlb/up/adopt/sm_1135767_1773831840_9391.jpg",
    "link": "https://sosyal.petlebi.com/kopek-sahiplenme/1135767-sokaga-terketilmis-kirma-yavru"
  },
  {
    "ilan_turu": "Sahiplendirme",
    "baslik": "Neşeli küçük köpek, bahçesi olan bir ev arıyor.",
    "aciklama": "Küçük boy, beyaz renkli, çok hareketli, koşmayı ve oynamayı seven, diğer köpekler ve kedilerle iyi geçinen bir Terrier.",
    "konum": "İzmir",
    "tarih1": "18.03.2026",
    "tarih2": "2026-03-18T00:00:00Z",
    "kategori": "Köpek",
    "gorsel": "https://images.petlebi.com/v7/_ptlb/up/adopt/sm_1135761_1773831482_9386.jpg",
    "link": "https://sosyal.petlebi.com/kopek-sahiplenme/1135761-neseli-kucuk-kopek-bahcesi-olan-bir-ev-ariyor"
  },
  {
    "ilan_turu": "Sahiplendirme",
    "baslik": "Gölge Erkek Blue French",
    "aciklama": "Eşimle ABD ye kesin dönüş yapacağımız için, çok sevdiğimiz erkek Blue Fransız Bulldog köpeğimizi kendisine bakabilecek iyi bir aileye sahiplendirmek istiyoruz. Köpeğimiz erkek tam 2 yaş 3 aylıktır. Çok oyuncu ve sevecen, ilgi seven bir köpektir. Sahiplenmek isteyecek kişilerin, maddi manevi sorumluluğunu alabilecek ve aile içinde iyi bir yuva sunabilecek olmalarını talep ediyoruz. Saat 18’den sonra aramayınız ayrıca mesaj atmayınız. Atılan mesajlarda kendisini tanıtmayan, veya selamınaleykum köpeği almak istiyorum ev nerede gibi soru soranlara sahiplendirilmeyecektir. Aile olması şartımızdır.",
    "konum": "İstanbul",
    "tarih1": "18.03.2026",
    "tarih2": "2026-03-18T00:00:00Z",
    "kategori": "Köpek",
    "gorsel": "https://images.petlebi.com/v7/_ptlb/up/adopt/sm_1135734_1773819316_9188.jpg",
    "link": "https://sosyal.petlebi.com/kopek-sahiplenme/1135734-golge-erkek-blue-french"
  },
  {
    "ilan_turu": "Sahiplendirme",
    "baslik": "Acil yuva aranıyor",
    "aciklama": "Acil yuva aranıyor\nMerhaba yavrumuzun ismi Mia. Dişi 3 buçuk aylık çok sağlıklı uysal sevecen bir bebek..aşılarını oldu.. tuvalet eğitimi var ömürlük onu çok sevecek yuvasını arıyorum\n.sahiplenmek isteyenler lütfen iletişime geçsin\nİstanbul beylikdüzü\n0531 589 78 12",
    "konum": "İstanbul",
    "tarih1": "18.03.2026",
    "tarih2": "2026-03-18T00:00:00Z",
    "kategori": "Köpek",
    "gorsel": "https://images.petlebi.com/v7/_ptlb/up/adopt/sm_1135710_1773809959_2138.jpg",
    "link": "https://sosyal.petlebi.com/kopek-sahiplenme/1135710-acil-yuva-araniyor"
  }
]