[
  {
    "ilan_turu": "Kayıp",
    "baslik": "Kayıp kedi Elazığ'da",
    "aciklama": "Gece apartmandan çıktı ve bulamadık Abdullahpaşada oturuyoruz Elazığ çevresinde her yerde olabilir Bulursanız lütfen iletişime geçin",
    "konum": "Elazığ / Merkez",
    "tarih1": "3 Saat Önce",
    "tarih2": "2026-03-12T06:34:33Z",
    "kategori": "Kedi",
    "gorsel": "https://www.gorenduyan.com/images/ad/2026/03/12/202603120952-23819-18158.jpg",
    "link": "https://www.gorenduyan.com/kayip-kedi-elazigda-21457"
  },
  {
    "ilan_turu": "Kayıp",
    "baslik": "Kedim kayıp aranıyor",
    "aciklama": "Kedim 11 Mart Çarşamba 2026 Tarihinde\nBurdur Merkez Atatürk Mahallesi Uğur\nMumcu Caddesinde Kaybolmuştur\nÜzerinde Kirazlı Taşması Var Sarman Adı\nTarçın gözleri yeşil renkte 8 Aylık Gören\nOlursa Allah Rızası Için Bana Ulaşabilirmi Mumaram 05539740821",
    "konum": "Burdur Merkez, Burdur",
    "tarih1": "10 Saat Önce",
    "tarih2": "2026-03-11T23:34:34Z",
    "kategori": "Kedi",
    "gorsel": "https://www.gorenduyan.com/images/ad/2026/03/12/202603120243-23817-53424.jpg",
    "link": "https://www.gorenduyan.com/kedim-kayip-araniyor-21455"
  },
  {
    "ilan_turu": "Kayıp",
    "baslik": "Kayıp kedi",
    "aciklama": "Rengi boz, 10 aylık dişi kedi. Esenyurt Büyükçekmece civarı kayıp. Bu alanlarda olduğunu düşünüyoruz.",
    "konum": "İstanbul - Gökevler",
    "tarih1": "11 Saat Önce",
    "tarih2": "2026-03-11T22:34:36Z",
    "kategori": "Kedi",
    "gorsel": "https://www.gorenduyan.com/images/ad/2026/03/12/202603120141-23816-48863.jpg",
    "link": "https://www.gorenduyan.com/kayip-kedi-21454"
  },
  {
    "ilan_turu": "Kayıp",
    "baslik": "Kayıp Pendik ve çevresi",
    "aciklama": "İsmi Max yüzünde küçük yara izi vardır tasmalı şekilde kayboldu",
    "konum": "İstanbul - Hocapaşa",
    "tarih1": "12 Saat Önce",
    "tarih2": "2026-03-11T21:34:39Z",
    "kategori": "Köpek",
    "gorsel": "https://www.gorenduyan.com/images/ad/2026/03/12/202603120045-23815-35042.jpg",
    "link": "https://www.gorenduyan.com/kayip-pendik-ve-cevresi-21453"
  },
  {
    "ilan_turu": "Sahiplendirme",
    "baslik": "Dünya Tatlısı Kedimiz",
    "aciklama": "3 aydir eevimdebaktigimdün ya tatlisi kedimi Mia Yi  surekli sehir rdisina ciktigimdan dolayi. Ona sevgisini verecek birine  sahiplendirmek istiyor um. Oyuncu bir kedidir .",
    "konum": "Trabzon / Ortahisar",
    "tarih1": "12.03.2026",
    "tarih2": "2026-03-12T00:00:00Z",
    "kategori": "Kedi",
    "gorsel": "https://www.petcim.com/pictures_ilan/mini_063f3d988ce6373c3ab43ff6719fea52.jpg",
    "link": "https://www.petcim.com/kedi-dunya-tatlisi-kedimiz-ilandetay-1345954"
  },
  {
    "ilan_turu": "Sahiplendirme",
    "baslik": "Dünya tatlısı British Shorthair",
    "aciklama": "British shorthair yavrumuz 5 aylık. Yeni yuvasını arıyor. Kuru mama ve kum eğitimi  tamamlandı. Oyuncu swvecen hareketli bir kedi.",
    "konum": "Gaziantep / Şehitkamil",
    "tarih1": "12.03.2026",
    "tarih2": "2026-03-12T00:00:00Z",
    "kategori": "Kedi",
    "gorsel": "https://www.petcim.com/pictures_ilan/mini_e2f4f86bed3c7ba0b6dc822168018f71.jpg",
    "link": "https://www.petcim.com/kedi-dunya-tatlisi-british-shorthair-ilandetay-1345953"
  },
  {
    "ilan_turu": "Sahiplendirme",
    "baslik": "Siyam kedisi oğluma yuva arıyorum",
    "aciklama": "Oğluma yuva arıyorum 11 aylık erkek tuvalet eğtimi falan var mama yiyior çok akıllı hastamız olduğu için bakamıyoruz",
    "konum": "İzmir / Bornova",
    "tarih1": "12.03.2026",
    "tarih2": "2026-03-12T00:00:00Z",
    "kategori": "Kedi",
    "gorsel": "https://www.petcim.com/pictures_ilan/mini_4e6809c0f1b526c5dcad3342adbfdde9.jpg",
    "link": "https://www.petcim.com/kedi-siyam-kedisi-ogluma-yuva-ariyorum-ilandetay-1345933"
  },
  {
    "ilan_turu": "Sahiplendirme",
    "baslik": "Scottish Fold Kedimiz 1 Yaşında",
    "aciklama": "1 yaşında Scottish cins kedi aşıları tam uysal sakin  evde küçük çocuk olduğu için bakımı zor Kastamonu Taşköprü",
    "konum": "Kastamonu / Taşköprü",
    "tarih1": "12.03.2026",
    "tarih2": "2026-03-12T00:00:00Z",
    "kategori": "Kedi",
    "gorsel": "https://www.petcim.com/pictures_ilan/mini_189374b718a5fb823e08d327e7e4ddc7.jpg",
    "link": "https://www.petcim.com/kedi-scottish-fold-kedimiz-1-yasinda-ilandetay-1345930"
  },
  {
    "ilan_turu": "Sahiplendirme",
    "baslik": "British shorthair",
    "aciklama": "Detaylı bilgi için whatsapp tan mesaj atabilirsinizSamsun ilkadimSadece whatsapp",
    "konum": "Samsun / İlkadım",
    "tarih1": "12.03.2026",
    "tarih2": "2026-03-12T00:00:00Z",
    "kategori": "Kedi",
    "gorsel": "https://www.petcim.com/pictures_ilan/mini_d58e75865a5f1e918656b7db4134144a.jpg",
    "link": "https://www.petcim.com/kedi-british-shorthair-ilandetay-1345915"
  },
  {
    "ilan_turu": "Sahiplendirme",
    "baslik": "Gri eğitimli british longhair yavru",
    "aciklama": "2 aylıktır. Tuvalet eğitimi vardır. Teması çok sever insan yanından ayrılmaz oyuncudur.",
    "konum": "Kocaeli / İzmit",
    "tarih1": "12.03.2026",
    "tarih2": "2026-03-12T00:00:00Z",
    "kategori": "Kedi",
    "gorsel": "https://www.petcim.com/pictures_ilan/mini_4135319c5b2f48a81c609d5c3b7a7b6c.jpeg",
    "link": "https://www.petcim.com/kedi-gri-egitimli-british-longhair-yavru-ilandetay-1345888"
  },
  {
    "ilan_turu": "Sahiplendirme",
    "baslik": "DİŞİ YAVRU 70 GÜNLÜK POİNT BRİTİSH SHORTHAİR",
    "aciklama": "british point dişi yavru eğitimleri tamamlandı cana yakın ev ortamında büğüdü..",
    "konum": "Kocaeli / Derince",
    "tarih1": "12.03.2026",
    "tarih2": "2026-03-12T00:00:00Z",
    "kategori": "Kedi",
    "gorsel": "https://www.petcim.com/pictures_ilan/mini_ef3496ff2e530fa23e77510c7e87c79a.jpg",
    "link": "https://www.petcim.com/kedi-disi-yavru-70-gunluk-point-british-shorthair-ilandetay-1345912"
  },
  {
    "ilan_turu": "Sahiplendirme",
    "baslik": "Top kafa özel scottish fold yavrular",
    "aciklama": "İlk aşıları yapıldı evde büyüdüler kuru mama yiyorlar kuma eğitimleri var çocuklarla uyumlu oyuncu çocuklar",
    "konum": "İstanbul / Eyüp",
    "tarih1": "12.03.2026",
    "tarih2": "2026-03-12T00:00:00Z",
    "kategori": "Kedi",
    "gorsel": "https://www.petcim.com/pictures_ilan/mini_0a31301a95a0f9df4141d0e836e5d7be.jpeg",
    "link": "https://www.petcim.com/kedi-top-kafa-ozel-scottish-fold-yavrular-ilandetay-1345910"
  },
  {
    "ilan_turu": "Sahiplendirme",
    "baslik": "Scottish Fold Yavrular",
    "aciklama": "Scottish Fold Blue 2 aylık yavrumuz kuru mamaya geçti kum alışkanlığı var anne Scottish baba British detaylı bilgi için ulaşabilirsiniz",
    "konum": "İstanbul / Eyüp",
    "tarih1": "12.03.2026",
    "tarih2": "2026-03-12T00:00:00Z",
    "kategori": "Kedi",
    "gorsel": "https://www.petcim.com/pictures_ilan/mini_12c5afa15b20de0c43d6d817bf81f306.jpeg",
    "link": "https://www.petcim.com/kedi-scottish-fold-yavrular-ilandetay-1345903"
  },
  {
    "ilan_turu": "Sahiplendirme",
    "baslik": "British Shorthair Blue Point Yavru",
    "aciklama": "2 aylık Bluepoint yavrumuz kuru mamaya geçti tuvalet eğitimi tamam anne babası Briitsh detaylı bilgi için ulaşabilirsiniz",
    "konum": "İstanbul / Gaziosmanpaşa",
    "tarih1": "12.03.2026",
    "tarih2": "2026-03-12T00:00:00Z",
    "kategori": "Kedi",
    "gorsel": "https://www.petcim.com/pictures_ilan/mini_db64d25a7ea5c20b3128efbf0f711d4a.jpeg",
    "link": "https://www.petcim.com/kedi-british-shorthair-blue-point-yavru-ilandetay-1345902"
  },
  {
    "ilan_turu": "Sahiplendirme",
    "baslik": "Scottish fold kar topuma güvenilir yuva",
    "aciklama": "Pamuk gibi oğlum çok uysal gerçekten sevicek ve ilgilenicek kişilere sahiplendirilicek 2 aylık kum eğitimi mevcut oyuncu ve kendini sevdiriyor",
    "konum": "Tekirdağ / Kapaklı",
    "tarih1": "12.03.2026",
    "tarih2": "2026-03-12T00:00:00Z",
    "kategori": "Kedi",
    "gorsel": "https://www.petcim.com/pictures_ilan/mini_d86ac5c52ee9fadce9db09a83fa39d22.jpg",
    "link": "https://www.petcim.com/kedi-scottish-fold-kar-topuma-guvenilir-yuva-ilandetay-1345891"
  },
  {
    "ilan_turu": "Sahiplendirme",
    "baslik": "Gri british longhair yavrumuz",
    "aciklama": "Yavrumuz 2 aylıktır. Tuvalet eğitimi vardır. İnsan canlısı temas bağımlısı ve oyuncu bir kedidir.",
    "konum": "Kocaeli / İzmit",
    "tarih1": "12.03.2026",
    "tarih2": "2026-03-12T00:00:00Z",
    "kategori": "Kedi",
    "gorsel": "https://www.petcim.com/pictures_ilan/mini_b25acfceb3acc08f6e3d22ec3792e54b.jpeg",
    "link": "https://www.petcim.com/kedi-gri-british-longhair-yavrumuz-ilandetay-1345869"
  },
  {
    "ilan_turu": "Sahiplendirme",
    "baslik": "Ayı kafa gri british longhair yavru",
    "aciklama": "2 aylıktır. Tuvalet eğitimi vardır. Ev ortamında doğup büyüyen yavrumuz insan yanından ayrılmaz oyun oynamayı çok sever",
    "konum": "Sakarya / Serdivan",
    "tarih1": "12.03.2026",
    "tarih2": "2026-03-12T00:00:00Z",
    "kategori": "Kedi",
    "gorsel": "https://www.petcim.com/pictures_ilan/mini_1464956838d5b90d27327de796f8f9fb.jpeg",
    "link": "https://www.petcim.com/kedi-ayi-kafa-gri-british-longhair-yavru-ilandetay-1345880"
  },
  {
    "ilan_turu": "Sahiplendirme",
    "baslik": "Çikolata rengi ayı kafa british shorthair yavru",
    "aciklama": "2aylıktır. Tuvalet eğitimi vardır. İnsan canlısıdır yanınızdan bir dakika ayrılmaz oyun oynamayı çok sever",
    "konum": "Sakarya / Serdivan",
    "tarih1": "12.03.2026",
    "tarih2": "2026-03-12T00:00:00Z",
    "kategori": "Kedi",
    "gorsel": "https://www.petcim.com/pictures_ilan/mini_de76f56fbc672a1b42fbdf54245039d0.jpeg",
    "link": "https://www.petcim.com/kedi-cikolata-rengi-ayi-kafa-british-shorthair-yavru-ilandetay-1345885"
  },
  {
    "ilan_turu": "Sahiplendirme",
    "baslik": "Ayı kafa eğitimli british longhair yavru",
    "aciklama": "Yavrumuz 2 aylıktır. Tuvalet eğitimi vardır. Ev ortamında doğup büyüyen bebeğimiz uysaldır. Yanınızdan ayrılmazkendşni sevdirmeyi çok sever.",
    "konum": "Sakarya / Serdivan",
    "tarih1": "12.03.2026",
    "tarih2": "2026-03-12T00:00:00Z",
    "kategori": "Kedi",
    "gorsel": "https://www.petcim.com/pictures_ilan/mini_f79e5d26a41ab81df1c3a62843012578.jpeg",
    "link": "https://www.petcim.com/kedi-ayi-kafa-egitimli-british-longhair-yavru-ilandetay-1345883"
  },
  {
    "ilan_turu": "Sahiplendirme",
    "baslik": "Golden Bebeklerimiz Aşıları Tam",
    "aciklama": "BİR ÇOK KÖPEK IRKLARININ DIŞINDA EV ORTAMINDA RAHATLIKLA BESLEYEBİLECEĞİNİZ SAYILI KÖPEK IRKLARINDAN OLAN UFAK IRKLARIMIZ İLE'de YANINIZDAYIZ. EĞİTMEN ARKADAŞLARIMIZ TARAFINDAN YAVRULARIMIZIN 15 GÜNLÜK SOSYALİZASYON İŞLEMLERİ TAMALANIP SİZLERİN YAŞAM STANDARTLARINA DAHA RAHAT AYAK UYDURABİLMESİ SAĞLANMAKTADIR. VETERİNER HEKİM KONTROLLERİ TAMAMLANIP KARANTİNA SÜREÇLERİNİ GEÇTİKTEN İLK AŞILAMALARIMIZ UYGULANDIKTAN SONRA EN ÖNEMLİSİ 15 GÜNLÜK SOSYALİZASYON İŞLEMLERİ TAMAMLANDIKTAN SONRA YAVRULARIMIZI SİZLERLE BULUŞTURUYORUZ. İLETİŞİM KURDUĞUNUZ YERLERİN BU KONUDA TAM DONANIMA SAHİP OLDUĞUNDAN EMİN OLDUKTAN SONRA YAVRU SAHİPLENMENİZİ ÖNERİYORUZ . UNUTMAYALIM Kİ SAHİPLENECEĞİNİZ YAVRU SAĞLIK KONTROLLERİNDEN VE IRK KONTROLLERİNDEN GEÇMİŞ FCI AKC ANKC'den TAM NOT ALMIŞ ANNE BABA'nın YAVRUSU OLMASINA ÖZEN GÖSTERİN İLETİŞİM KURDUĞUNUZ YERLERE BU SORULARI SORMAYI UNUTMAYIN 15 SENE BOYUNCA KENDİNİZE BİR DOST SAHİPLENDİĞİNİZİ VE AİLENİZİN BİR PARÇASI OLUCAĞININ BİZLER FARKINDAYIZ VE YAŞAMINIZ BOYUNCA SİZLERE YAŞAM BOYU BİRLİKTE OLMA SÖZÜ VERİYORUZ.",
    "konum": "İstanbul / Çekmeköy",
    "tarih1": "12.03.2026",
    "tarih2": "2026-03-12T00:00:00Z",
    "kategori": "Köpek",
    "gorsel": "https://www.petcim.com/pictures_ilan/mini_7086f7a2c7289b470127e6b380d28705.jpg",
    "link": "https://www.petcim.com/kopek-golden-bebeklerimiz-asilari-tam-ilandetay-1346347"
  },
  {
    "ilan_turu": "Sahiplendirme",
    "baslik": "Son 2 dişi yavru cocker",
    "aciklama": "Amerikan cocker son 2 dişi yavru şuan 45 günlükler yavru kuru mamaya alıştılarYer : MERSİN",
    "konum": "Mersin / Yenişehir",
    "tarih1": "12.03.2026",
    "tarih2": "2026-03-12T00:00:00Z",
    "kategori": "Köpek",
    "gorsel": "https://www.petcim.com/pictures_ilan/mini_8b3568c21237b8829f172cd488ff73b2.jpg",
    "link": "https://www.petcim.com/kopek-son-2-disi-yavru-cocker-ilandetay-1345962"
  },
  {
    "ilan_turu": "Sahiplendirme",
    "baslik": "4 AYLIK ERKEK TERRİER TUVALET EĞİTİMİ VE AŞILARI TAM",
    "aciklama": "ismi boncuk 4 aylık erkek oyuncu ısırma huyu kesinlikle yokturtuvalet eğitimi var aşıları ve kimlik kartı mevcut mama veriyoruzharici bir çok şeyi de yiyor yanında kulübesi de verileceksaldırma huyları vs kesinlikle yoktur ücre tlidir ona göre yazarsanız sevinirimWHATSAPP DAN ULAŞIN DETAYLI VİDEOLARI ATAYIM",
    "konum": "Malatya / Yeşilyurt",
    "tarih1": "12.03.2026",
    "tarih2": "2026-03-12T00:00:00Z",
    "kategori": "Köpek",
    "gorsel": "https://www.petcim.com/pictures_ilan/mini_616a3bddf49137c67d85998c66be9549.jpeg",
    "link": "https://www.petcim.com/kopek-4-aylik-erkek-terrier-tuvalet-egitimi-ve-asilari-tam-ilandetay-1345934"
  },
  {
    "ilan_turu": "Sahiplendirme",
    "baslik": "3 yaşında scottish fold",
    "aciklama": "3 yaşında kısır çipi aşısı var yalnız kalmayı sevmez kendini sevdirir sürekli temas halinde olmayı çok seviyor taranmayı çok seviyor",
    "konum": "Antalya",
    "tarih1": "12.03.2026",
    "tarih2": "2026-03-12T00:00:00Z",
    "kategori": "Kedi",
    "gorsel": "https://images.petlebi.com/v7/_ptlb/up/adopt/sm_1133762_1773304370_4874.jpg",
    "link": "https://sosyal.petlebi.com/kedi-sahiplenme/1133762-3-yasinda-scottish-fold"
  },
  {
    "ilan_turu": "Sahiplendirme",
    "baslik": "KUCAK KEDİSİ KÖFTE YUVA ARIYOR",
    "aciklama": "Yine terk edilme hikayesi… Çok cana yakın kucak kedisi Köfteye acil yuva arıyoruz. Bi anda iş yerimizin bahçesine geldi, belli ki evden bırakılmış… Kısır, erkek, 2 yaşlarında, aşıları tamam, veteriner kontrolü yapıldı gayet sağlıklı. Tek eksiği yeni yuvası… Ankara içi nakli sağlanacaktır. İletişim : 0532 798 77 91",
    "konum": "Ankara",
    "tarih1": "12.03.2026",
    "tarih2": "2026-03-12T00:00:00Z",
    "kategori": "Kedi",
    "gorsel": "https://images.petlebi.com/v7/_ptlb/up/adopt/sm_1133789_1773305742_5093.jpg",
    "link": "https://sosyal.petlebi.com/kedi-sahiplenme/1133789-kucak-kedisi-kofte-yuva-ariyor"
  },
  {
    "ilan_turu": "Sahiplendirme",
    "baslik": "MAVİŞ HALA YUVASIZ",
    "aciklama": "Sokakta beslediğimiz Maviş kızımıza yuva arıyoruz. İsmini biliyor 🤭 Tam bir piremses, nazlı nazlı gelip sevdiriyor kendini. Kısırlaştırıldı. Bu güzellikle daha fazla dışarda yaşamasın. Ankara içi nakli sağlanacaktır. İletişim : 0532 798 77 91",
    "konum": "Ankara",
    "tarih1": "12.03.2026",
    "tarih2": "2026-03-12T00:00:00Z",
    "kategori": "Kedi",
    "gorsel": "https://images.petlebi.com/v7/_ptlb/up/adopt/sm_1133786_1773305276_8013.jpg",
    "link": "https://sosyal.petlebi.com/kedi-sahiplenme/1133786-mavis-hala-yuvasiz"
  },
  {
    "ilan_turu": "Sahiplendirme",
    "baslik": "ÖKSÜZ HALA YUVASIZ",
    "aciklama": "Bu oğluşu belediyeye kısırlaştırmaya bırakmışlar almamışlar. Bilinmez bi alana bırakılmasın diye bahçemize aldık. Muhtemelen daha önce de bi evdeydi tüyleri çok temiz ve yumuşak. Geçmişiyle ilgili maalesef bi bilgimiz yok tek bildiğimiz kısırlaştırıldığı. Çok sevecen kucak kedisi, başka kedilerle de anlaşıyor aşırı mülayim bi çocuk. Hatta sevgilisi de var mümkünse beraber bir evleri olsun istiyoruz 🤭 Ankara içi nakli sağlanacaktır. İletişim : 0532 798 77 91",
    "konum": "Ankara",
    "tarih1": "12.03.2026",
    "tarih2": "2026-03-12T00:00:00Z",
    "kategori": "Kedi",
    "gorsel": "https://images.petlebi.com/v7/_ptlb/up/adopt/sm_1133783_1773305195_5678.jpg",
    "link": "https://sosyal.petlebi.com/kedi-sahiplenme/1133783-oksuz-hala-yuvasiz"
  },
  {
    "ilan_turu": "Sahiplendirme",
    "baslik": "İPEK HALA YUVASIZ",
    "aciklama": "Sırtında kocaman yarasıyla bi anda besleme alanımıza gelince tanıştık İpek kızımızla. Yarası iyileşene kadar tedavi ettikten sonra bi daha ayrılmadı yanımızdan. İyileşmek için bizi bulan bu kıza şimdi sıcak bir yuva arıyoruz. Tam bir kız çocuğu cıvıl cıvıl. Diğer kedilerle de anlaşıyor, yemeğini bölüşen insanlara kafasını sürterek teşekkür ediyor 🤭 ipek kızımıza yuvasını açmak isteyen olur mu? Kısır, kuduz aşısı yapıldı. Ankara içi nakli sağlanacaktır. İletişim : 0532 798 77 91",
    "konum": "Ankara",
    "tarih1": "12.03.2026",
    "tarih2": "2026-03-12T00:00:00Z",
    "kategori": "Kedi",
    "gorsel": "https://images.petlebi.com/v7/_ptlb/up/adopt/sm_1133780_1773305104_8371.jpg",
    "link": "https://sosyal.petlebi.com/kedi-sahiplenme/1133780-ipek-hala-yuvasiz"
  },
  {
    "ilan_turu": "Sahiplendirme",
    "baslik": "ÇARŞI HALA YUVASIZ",
    "aciklama": "Besleme alanından sürgüne gönderildi. Bırakıldığı yerde yaşaması çok zordu, bu yüzden tekrar gidip alarak eski yerine getirdik. Yalancı gebelik geçirdi; yanındaki yavru kedileri kendi yavrusu gibi sevdi, korudu ve besledi… Çocuklarla da arası çok iyi.\nBu kadar anaç ve sevgi dolu bir kedinin sokakta yaşamasını istemiyoruz.\nTedavileri tamamlandı, sağlığı çok iyi.\nAnkara içi nakil mümkündür.\n📞 İletişim: 0532 798 77 91",
    "konum": "Ankara",
    "tarih1": "12.03.2026",
    "tarih2": "2026-03-12T00:00:00Z",
    "kategori": "Kedi",
    "gorsel": "https://images.petlebi.com/v7/_ptlb/up/adopt/sm_1133777_1773305024_7990.jpg",
    "link": "https://sosyal.petlebi.com/kedi-sahiplenme/1133777-carsi-hala-yuvasiz"
  },
  {
    "ilan_turu": "Sahiplendirme",
    "baslik": "MOCHA HALA YUVASIZ",
    "aciklama": "Bu güzel desenli çocuğu maalesef evden atıp besleme alanımıza bıraktılar… Erkek, 1 yaşından küçük olduğunu düşünüyoruz… Kısırlaştırıp kuduz aşısını yapıp sahiplendirmek istiyoruz. Yuvanızı açmak ister misiniz? Ankara içi nakli sağlanacaktır. İletişim : 0532 798 77 91",
    "konum": "Ankara",
    "tarih1": "12.03.2026",
    "tarih2": "2026-03-12T00:00:00Z",
    "kategori": "Kedi",
    "gorsel": "https://images.petlebi.com/v7/_ptlb/up/adopt/sm_1133774_1773304883_8026.jpg",
    "link": "https://sosyal.petlebi.com/kedi-sahiplenme/1133774-mocha-hala-yuvasiz"
  },
  {
    "ilan_turu": "Sahiplendirme",
    "baslik": "BENEKLİ HALA YUVA ARIYOR",
    "aciklama": "Yine bi evden atılma hikayesi… Bu güzel huylu çocuğu sağlık ocağında gördüm. Yaklaşık 1 ay kadar önce orda belirmiş birden. Mesai saatlerinde içerde, tabi hastalar müsaade ettiği sürece. Mesai bitimi mecbur sokaktaymış. Sahibini bulamamışlar. Şansımızı denemek istiyoruz. Yaklaşık 2-3 yaşlarında, erkek, kısır, hemşirenin anlattığına göre çok uysal,sakin, insan canlısı bir çocukmuş. Bu oğluşa 2.bahar yaşatmak ister misiniz? Ankara içi nakli sağlanacaktır. İletişim : 0532 798 77 91",
    "konum": "Ankara",
    "tarih1": "12.03.2026",
    "tarih2": "2026-03-12T00:00:00Z",
    "kategori": "Kedi",
    "gorsel": "https://images.petlebi.com/v7/_ptlb/up/adopt/sm_1133771_1773304777_506.jpg",
    "link": "https://sosyal.petlebi.com/kedi-sahiplenme/1133771-benekli-hala-yuva-ariyor"
  },
  {
    "ilan_turu": "Sahiplendirme",
    "baslik": "KÖROZ HALA YUVA ARIYOR",
    "aciklama": "Tek gözü olmayan güzel kızımız için yuva arıyoruz. Yaklaşık 1 yıl kadar önce tek gözünü kaybetti ama neşesini sevgisini hiç kaybetmedi. Kısır dişi kedimiz Köroz nerdeyse 2 yaşında ve hep sokakta. Artık sokakta yaşamasın, bi şansı varsa onun da evi olsun istiyoruz. Bu cilveli narin kızımıza evini açmak isteyen olur mu? Başka kedilerle anlaşıyor ve insan aşığı bi çocuk. Ankara içi nakli sağlanacaktır. İletişim : 0532 798 77 91",
    "konum": "Ankara",
    "tarih1": "12.03.2026",
    "tarih2": "2026-03-12T00:00:00Z",
    "kategori": "Kedi",
    "gorsel": "https://images.petlebi.com/v7/_ptlb/up/adopt/sm_1133768_1773304681_5672.jpg",
    "link": "https://sosyal.petlebi.com/kedi-sahiplenme/1133768-koroz-hala-yuva-ariyor"
  },
  {
    "ilan_turu": "Sahiplendirme",
    "baslik": "İKİSİ DE VAN MELEZİ ASLINDA ÇOOKK UYSALLAR‼️",
    "aciklama": "Birisi smokine birisi sarman ama aslında ikisi de Van melezi. Yaklaşık 4.5-5 aylıklar. Karakterleti oturmak üzere. Evde doğup büyüdüler. Ev terbiyeliler. Sağlık sorunları YOK ‼️İnsana düşkün, sımsıcak çocuklar. Sosyal ve uyumlular. Birbirlerine de düşkünler. Kalpten, candan gelerek bir canın patisinden tutup onun hayatına katkı olmayı amaçlayan, bir ömür onlardan birini ya da ikisini sarmalamayı seçen pamuk kalpli meleği sen olur musun⁉️ İletişim tel: +905359660837 Hatice hn KISIRLAŞTIRMASI TARAFIMDAN SAĞLANACAKTIR‼️YASALAR GEREĞİ ÇİP VE TAKİP ŞARTI VARDIR ‼️",
    "konum": "Bursa",
    "tarih1": "12.03.2026",
    "tarih2": "2026-03-12T00:00:00Z",
    "kategori": "Kedi",
    "gorsel": "https://images.petlebi.com/v7/_ptlb/up/adopt/sm_1133753_1773303145_6003.jpg",
    "link": "https://sosyal.petlebi.com/kedi-sahiplenme/1133753-ikisi-de-van-melezi-aslinda-cookk-uysallar"
  },
  {
    "ilan_turu": "Sahiplendirme",
    "baslik": "Acil sahiplendirilmesi gerek",
    "aciklama": "Çok tatlı bir kedi sakin uysal çok güzel dost olur bebeğim küçük olduğu için vermek zorundayım",
    "konum": "İstanbul",
    "tarih1": "12.03.2026",
    "tarih2": "2026-03-12T00:00:00Z",
    "kategori": "Kedi",
    "gorsel": "https://images.petlebi.com/v7/_ptlb/up/adopt/sm_1133747_1773301933_2325.jpg",
    "link": "https://sosyal.petlebi.com/kedi-sahiplenme/1133747-acil-sahiplendirilmesi-gerek"
  },
  {
    "ilan_turu": "Sahiplendirme",
    "baslik": "Smokin kız güzelliği",
    "aciklama": "31 aralikta 2025 in son güzelliği olarak dogan kızımız evde büyüdü. Kum kullanıyor yaş kuru mama yiyor. Inanilmaz cana yakın sizi gördüğü an gurlamaya başlıyor. Kimi zaman sokulup kucakta uyur kimi zaman oyunlariyla sizi güldürür. Smokin kediler sahibiyle bağ kurar ve ona cok ozel hissettirir. En tatli zamanlarindaki bu güzel kızı alip kendinize aşık edin :) 25 yas üstü kedi tecrubesi olan ve kısırlaştırma yaptırıp camlara kedi teli yaptiracak kisilere sahiplendirilecektir.",
    "konum": "Ankara",
    "tarih1": "12.03.2026",
    "tarih2": "2026-03-12T00:00:00Z",
    "kategori": "Kedi",
    "gorsel": "https://images.petlebi.com/v7/_ptlb/up/adopt/sm_1133744_1773302062_1086.jpg",
    "link": "https://sosyal.petlebi.com/kedi-sahiplenme/1133744-smokin-kiz-guzelligi"
  },
  {
    "ilan_turu": "Sahiplendirme",
    "baslik": "Tek göz Mike Wazowski yuvasını arıyor.",
    "aciklama": "Dünyaya iki gözünü açarak başlamıştı fakat geçirdiği araba kazası sonucu tek gözüyle yaşama tutundu. Sitemizde baktığımız bu güzel kız çok uysal ve sevecen. Kazadan sonra 3. ay veterinerde kaldı. Tamamen iyileşti fakat zaten ürkek yapısı tek gözlü kalmasından iyice ürkekleşti ve diğer kediler tarafından zorbalanıyor. Tam ev kedisi olacak bir yapısı var bu yüzden ömürlük yuvasını arıyoruz",
    "konum": "İstanbul",
    "tarih1": "12.03.2026",
    "tarih2": "2026-03-12T00:00:00Z",
    "kategori": "Kedi",
    "gorsel": "https://images.petlebi.com/v7/_ptlb/up/adopt/sm_1133735_1773301655_6983.jpg",
    "link": "https://sosyal.petlebi.com/kedi-sahiplenme/1133735-tek-goz-mike-wazowski-yuvasini-ariyor"
  },
  {
    "ilan_turu": "Sahiplendirme",
    "baslik": "Hareketli ve atil",
    "aciklama": "3 yaşında olup gayet sağlıklı bir kedimiz çok enerjik kısırlaştırılma yapılmadı!aile evinde olduğu için annem artık bakamıyor bu yüzden kedileri seven bir hayvan sever dostumuza vermek isteriz aşıları tam",
    "konum": "Elazığ",
    "tarih1": "12.03.2026",
    "tarih2": "2026-03-12T00:00:00Z",
    "kategori": "Kedi",
    "gorsel": "https://images.petlebi.com/v7/_ptlb/up/adopt/sm_1133690_1773285108_7886.jpg",
    "link": "https://sosyal.petlebi.com/kedi-sahiplenme/1133690-hareketli-ve-atil"
  },
  {
    "ilan_turu": "Sahiplendirme",
    "baslik": "Yakışıklıya ömürlük yuva arıyoruz",
    "aciklama": "Yakışıklı oğlumuz 8 aylık oyuncu sakin çok tatlı tuvalet eğitimi var mama yiyor",
    "konum": "Bursa",
    "tarih1": "12.03.2026",
    "tarih2": "2026-03-12T00:00:00Z",
    "kategori": "Kedi",
    "gorsel": "https://images.petlebi.com/v7/_ptlb/up/adopt/sm_1133675_1773266739_1197.jpg",
    "link": "https://sosyal.petlebi.com/kedi-sahiplenme/1133675-yakisikliya-omurluk-yuva-ariyoruz"
  },
  {
    "ilan_turu": "Sahiplendirme",
    "baslik": "Bu kızımıza acil yuva arıyoruz",
    "aciklama": "Kızımız bir yaşında kısır mama yiyor tuvalet alışkanlığı var ona ömürlük yuva arıyoruz",
    "konum": "Bursa",
    "tarih1": "12.03.2026",
    "tarih2": "2026-03-12T00:00:00Z",
    "kategori": "Kedi",
    "gorsel": "https://images.petlebi.com/v7/_ptlb/up/adopt/sm_1133672_1773266598_8061.jpg",
    "link": "https://sosyal.petlebi.com/kedi-sahiplenme/1133672-bu-kizimiza-acil-yuva-ariyoruz"
  },
  {
    "ilan_turu": "Sahiplendirme",
    "baslik": "Gümüş yuva arıyor",
    "aciklama": "Eşimin alerjisinden ötürü sahiplendiriyoruz aşıları tam kısırlaştırılmış çipi var devredilecek sadece uysal kendi halinde bir kedi kalıcı yuvasını arıyor umarız",
    "konum": "İzmir",
    "tarih1": "12.03.2026",
    "tarih2": "2026-03-12T00:00:00Z",
    "kategori": "Kedi",
    "gorsel": "https://images.petlebi.com/v7/_ptlb/up/adopt/sm_1133657_1773264020_2237.jpg",
    "link": "https://sosyal.petlebi.com/kedi-sahiplenme/1133657-gumus-yuva-ariyor"
  },
  {
    "ilan_turu": "Sahiplendirme",
    "baslik": "Dişi-kısır- oyuncu-korumacı-",
    "aciklama": "Ordu Altınordu da mahallemizde kısırlaştırdığımız köpeklerden. Çok oyuncu insana yakın, diğer köpeklerle de arası iyi. Ona bahçeli korunaklı bir alan arıyoruz.",
    "konum": "Ordu",
    "tarih1": "12.03.2026",
    "tarih2": "2026-03-12T00:00:00Z",
    "kategori": "Köpek",
    "gorsel": "https://images.petlebi.com/v7/_ptlb/up/adopt/sm_1133732_1773301380_1339.jpg",
    "link": "https://sosyal.petlebi.com/kopek-sahiplenme/1133732-disi-kisir-oyuncu-korumaci-"
  },
  {
    "ilan_turu": "Sahiplendirme",
    "baslik": "🐶 ACİL YUVA ARANIYOR – JESSY",
    "aciklama": "Jessy 2 yaşında, orta boy Kokoni kırması bir köpektir. Yaklaşık 1 yıl önce sokakta buldum ve o zamandan beri evimde bakıyorum. Çipli, aşıları tam ve temel komutları dinleyen akıllı bir köpektir. Ayrıca ped eğitimi vardır ve ev ortamına alışkındır.Jessy çok sevecen, insanlara karşı sıcak ve tam bir sevgi arsızıdır. İlgi görmeyi ve insanlarla vakit geçirmeyi çok sever.Ancak apartman dairesinde yaşadığım için zaman zaman çıkardığı sesler nedeniyle bina içinde ciddi şikayetler oluştu ve maalesef artık bakmaya devam edemiyorum.Onu kesinlikle sokağa bırakmak istemiyorum. Sevgi dolu, güvenli ve kalıcı bir yuva bulmasını istiyorum.Gerçekten sahiplenmek isteyen ve ona güzel bir hayat sunabilecek kişiler benimle iletişime geçerse çok sevinirim.📍 İstanbul",
    "konum": "İstanbul",
    "tarih1": "12.03.2026",
    "tarih2": "2026-03-12T00:00:00Z",
    "kategori": "Köpek",
    "gorsel": "https://images.petlebi.com/v7/_ptlb/up/adopt/sm_1133693_1773286432_2996.jpg",
    "link": "https://sosyal.petlebi.com/kopek-sahiplenme/1133693-acil-yuva-araniyor-jessy"
  },
  {
    "ilan_turu": "Sahiplendirme",
    "baslik": "Şilaya geçici yuva",
    "aciklama": "Çok akıllı bir çocuk. Havlama ısırma huyu yok . Geçici yuva arıyoruz çok acil. Tüm eşyalarını vereceğim masraf yapmayacaksınız çok acil geçici yuva arıyoruz",
    "konum": "Ankara",
    "tarih1": "12.03.2026",
    "tarih2": "2026-03-12T00:00:00Z",
    "kategori": "Köpek",
    "gorsel": "https://images.petlebi.com/v7/_ptlb/up/adopt/sm_1133687_1773274459_7221.jpg",
    "link": "https://sosyal.petlebi.com/kopek-sahiplenme/1133687-silaya-gecici-yuva"
  },
  {
    "ilan_turu": "Sahiplendirme",
    "baslik": "Barınakta doğan bir can",
    "aciklama": "Annesi barınakta doğum yaptı anne beagle acil korumaya alındılar şuan pansiyondalar 5 Aralık doğumlu melez yavrulara yuva olabilecek ailelere sahiplendirmek istiyoruz..pansiyonda fazla tutamayız",
    "konum": "İstanbul",
    "tarih1": "11.03.2026",
    "tarih2": "2026-03-11T00:00:00Z",
    "kategori": "Köpek",
    "gorsel": "https://images.petlebi.com/v7/_ptlb/up/adopt/sm_1133609_1773252855_8230.jpg",
    "link": "https://sosyal.petlebi.com/kopek-sahiplenme/1133609-barinakta-dogan-bir-can"
  },
  {
    "ilan_turu": "Sahiplendirme",
    "baslik": "IKİSİ DE ÇİPLİ CORGİ MELEZLERİ ‼️",
    "aciklama": "Mini mini, güzel mi güzel ev terbiyeli, sımsıcacık 2 tane sevgi ponçiği. Birinin adı: FINDIK diğerinin adı: LOVELY. Fındık KISIR, Lovely DEĞİL❗️Sevimli ve cana yakınlar. Sosyal ve uyumlular. Sağlık sorunları YOK ‼️Tercihimiz ikisinin de birlikte aynı yuvaya sahiplenilmesi❗️Onlardan birini ya da ikisini birlikte kucaklayarak, şefkat ve sevgiyle bir ömür güvende tutacak sorumluluk sahibi melekleri sen olur musun⁉️\nİletişim tel:05364691231 YASALAR GEREĞİ ÇİP DEVRİ, KISIRLAŞTIRMA VE TAKİP ŞARTI VARDIR ‼️",
    "konum": "Bursa",
    "tarih1": "12.03.2026",
    "tarih2": "2026-03-12T00:00:00Z",
    "kategori": "Köpek",
    "gorsel": "https://images.petlebi.com/v7/_ptlb/up/adopt/sm_1133669_1773266564_3044.jpg",
    "link": "https://sosyal.petlebi.com/kopek-sahiplenme/1133669-corgi-melezleri-asili-ve-tuvalet-egitimli"
  },
  {
    "ilan_turu": "Sahiplendirme",
    "baslik": "Sokağa terkedilmiş poodle ailesini arıyor",
    "aciklama": "İstanbula getirebiliriz sahiplendirme için.Sokakta çok kötü bi halde başka köpeğin ağzında yakalayıp bulduk boynundan yaralanmıştı. Ameliyat ettirdik. Aşıları yapıldı şuan çok sağlıklı ve tüm bakımları yapıldı. Çok sakin. Tuvalet eğitimi var.  Ona çok iyi bakacak bir aile arıyoruz",
    "konum": "Elazığ",
    "tarih1": "11.03.2026",
    "tarih2": "2026-03-11T00:00:00Z",
    "kategori": "Köpek",
    "gorsel": "https://images.petlebi.com/v7/_ptlb/up/adopt/sm_1133558_1773243840_3734.jpg",
    "link": "https://sosyal.petlebi.com/kopek-sahiplenme/1133558-sokaga-terkedilmis-poodle-ailesini-ariyor"
  },
  {
    "ilan_turu": "Sahiplendirme",
    "baslik": "Marlamıza ömürlük yuva",
    "aciklama": "Marla uslu ve sevimli bir köpek.  Şuan geçici yuvada fakat kalıcı bir yuva arıyoruz. İzmir içi sahiplendirme  . WhatsApp üzerinden iletişim",
    "konum": "İzmir",
    "tarih1": "11.03.2026",
    "tarih2": "2026-03-11T00:00:00Z",
    "kategori": "Köpek",
    "gorsel": "https://images.petlebi.com/v7/_ptlb/up/adopt/sm_1133480_1773233337_4926.jpg",
    "link": "https://sosyal.petlebi.com/kopek-sahiplenme/1133480-marlamiza-omurluk-yuva"
  },
  {
    "ilan_turu": "Sahiplendirme",
    "baslik": "Güzel kızımız haçiko",
    "aciklama": "Haçiko oldukça uysal bir köpek.  Şuan geçici yuvasında fakat ona ömürlük yuvasını arıyoruz.  İzmir içi sahiplendirme.  WhatsApp üzerinden iletişim .",
    "konum": "İzmir",
    "tarih1": "11.03.2026",
    "tarih2": "2026-03-11T00:00:00Z",
    "kategori": "Köpek",
    "gorsel": "https://images.petlebi.com/v7/_ptlb/up/adopt/sm_1133477_1773233121_6496.jpg",
    "link": "https://sosyal.petlebi.com/kopek-sahiplenme/1133477-guzel-kizimiz-haciko"
  }
]